autoextract/__init__.py
autoextract/extract.py
autoextract-0.0.1.dist-info/LICENSE
autoextract-0.0.1.dist-info/METADATA
autoextract-0.0.1.dist-info/WHEEL
autoextract-0.0.1.dist-info/top_level.txt
autoextract-0.0.1.dist-info/RECORD
