Metadata-Version: 2.1
Name: autoextract
Version: 0.0.1
Summary: Extract important information from a text by just asking for it
Home-page: https://github.com/jamescalam/aesthetic_ascii
Author: Gyan Ranjan
Author-email: gyan7611@gmail.com
License: UNKNOWN
Platform: UNKNOWN
Classifier: Programming Language :: Python :: 3
Classifier: License :: OSI Approved :: MIT License
Classifier: Operating System :: OS Independent
Requires-Python: >=3.8
License-File: LICENSE
